eodag_sentinelsat/__init__.py
eodag_sentinelsat/eodag_sentinelsat.py
eodag_sentinelsat/providers.yml
eodag_sentinelsat-0.4.1.post1.dist-info/LICENSE
eodag_sentinelsat-0.4.1.post1.dist-info/METADATA
eodag_sentinelsat-0.4.1.post1.dist-info/NOTICE
eodag_sentinelsat-0.4.1.post1.dist-info/WHEEL
eodag_sentinelsat-0.4.1.post1.dist-info/entry_points.txt
eodag_sentinelsat-0.4.1.post1.dist-info/top_level.txt
eodag_sentinelsat-0.4.1.post1.dist-info/RECORD
