Metadata-Version: 2.1
Name: eodag-sentinelsat
Version: 0.4.1.post1
Summary: Sentinelsat plugin to EODAG (https://github.com/CS-SI/eodag)
Home-page: https://github.com/CS-SI/eodag-sentinelsat
Author: CS Systemes d'Information (CSSI)
Author-email: admin@geostorm.eu
License: GPLv3
Project-URL: Bug Tracker, https://github.com/CS-SI/eodag-sentinelsat/issues/
Project-URL: Documentation, https://github.com/CS-SI/eodagsentinelsat/blob/master/README.rst
Project-URL: Source Code, https://github.com/CS-SI/eodag-sentinelsat
Platform: UNKNOWN
Classifier: Development Status :: 5 - Production/Stable
Classifier: Intended Audience :: Developers
Classifier: Intended Audience :: Science/Research
Classifier: Natural Language :: English
Classifier: License :: OSI Approved :: GNU General Public License v3 or later (GPLv3+)
Classifier: Operating System :: Microsoft :: Windows
Classifier: Operating System :: POSIX :: Linux
Classifier: Programming Language :: Python :: 3
Classifier: Programming Language :: Python :: 3.6
Classifier: Programming Language :: Python :: 3.7
Classifier: Programming Language :: Python :: 3.8
Classifier: Programming Language :: Python :: 3.9
Classifier: Programming Language :: Python :: Implementation :: CPython
Classifier: Topic :: Internet :: WWW/HTTP :: Indexing/Search
Classifier: Topic :: Scientific/Engineering :: GIS
Classifier: Topic :: Software Development :: Libraries :: Python Modules
Requires-Dist: sentinelsat >=1.1.0
Requires-Dist: eodag >=2.3.0b1
Requires-Dist: python-dateutil
Provides-Extra: dev
Requires-Dist: pre-commit ; extra == 'dev'
Requires-Dist: tox ; extra == 'dev'
Requires-Dist: pytest ; extra == 'dev'
